<?xml version="1.0" encoding="UTF-8"?>
<beans xmlns="http://www.springframework.org/schema/beans"
       xmlns:xsi="http://www.w3.org/2001/XMLSchema-instance"
       xsi:schemaLocation="
       http://www.springframework.org/schema/beans http://www.springframework.org/schema/beans/spring-beans-3.0.xsd">

    <bean id="scenarioLoaderFactory" class="org.tanaguru.scenarioloader.ScenarioLoaderFactoryImpl">
        <property name="jsScriptMap">
            <map>
                <entry key="colorExtractor" value="/js/colorExtractor_nativeJs.js"/>
            </map>
        </property>
<!--        <property name="implicitelyWaitDriverTimeout">
            <value>5</value>
        </property>-->
        <property name="pageLoadDriverTimeout">
            <value>${pageLoadTimeout}</value>
        </property>
    </bean>

    <bean id="scenarioLoaderService" class="org.tanaguru.service.ScenarioLoaderServiceImpl"/>

    <bean id="profileFactory" class="org.tanaguru.sebuilder.tools.ProfileFactory" factory-method="getInstance"/>

<!--    <bean id="firefoxDriverPoolabelObjectFactory" class="org.tanaguru.sebuilder.tools.FirefoxDriverPoolableObjectFactory">
        <property name="implicitelyWaitDriverTimeout">
            <value>30</value>
        </property>
        <property name="pageLoadDriverTimeout">
            <value>10</value>
        </property>
    </bean>

    <bean id="firefoxDriverObjectPool" class="org.tanaguru.sebuilder.tools.FirefoxDriverObjectPool">
        <property name="maxActive">
            <value>10</value>
        </property>
        <property name="minIdle">
            <value>3</value>
        </property>
        <property name="minEvictableIdleTimeMillis">
             <value>10800000</value>  3 hours in ms
        </property>
        <property name="timeBetweenEvictionRunsMillis">
             <value>10800000</value>  3 hours in ms
        </property>
        <property name="whenExhaustedAction">
             <value>1</value>  WHEN_EXHAUSTED_FAIL= 0;WHEN_EXHAUSTED_BLOCK= 1; WHEN_EXHAUSTED_GROW= 2;
        </property>
        <property name="lifo">
             <value>true</value> 
        </property>
    </bean>-->

    <bean class="org.springframework.beans.factory.config.MethodInvokingFactoryBean">
        <property name="targetObject">
            <ref local="profileFactory"/>
        </property>
        <property name="targetMethod">
            <value>setProxyPort</value>
        </property>
        <property name="arguments">
            <list>
                <value>${proxyPort}</value>
            </list>
        </property>
    </bean>
    
    <bean class="org.springframework.beans.factory.config.MethodInvokingFactoryBean">
        <property name="targetObject">
            <ref local="profileFactory"/>
        </property>
        <property name="targetMethod">
            <value>setProxyHost</value>
        </property>
        <property name="arguments">
            <list>
                <value>${proxyHost}</value>
            </list>
        </property>
    </bean>
    
    <bean class="org.springframework.beans.factory.config.MethodInvokingFactoryBean">
        <property name="targetObject">
            <ref local="profileFactory"/>
        </property>
        <property name="targetMethod">
            <value>setProxyExclusionUrl</value>
        </property>
        <property name="arguments">
            <list>
                <value>${proxyExclusionUrl}</value>
            </list>
        </property>
    </bean>
    
    <bean class="org.springframework.beans.factory.config.MethodInvokingFactoryBean">
        <property name="targetObject">
            <ref local="profileFactory"/>
        </property>
        <property name="targetMethod">
            <value>setPathToPreSetProfile</value>
        </property>
        <property name="arguments">
            <list>
                <value>${pathToPreSetFirefoxProfile}</value>
            </list>
        </property>
    </bean>


</beans>